{
	"SpawnForced" : true,
	"SpawnWorld" : "world",
	"SpawnX" : 0,
	"SpawnY" : 62,
	"SpawnZ" : -8,
	"air" : 300,
	"enchantmentSeed" : 2726318631,
	"enderchestinventory" : 
	[
		{
			"ID" : -1
		},
		{
			"ID" : -1
		},
		{
			"ID" : -1
		},
		{
			"ID" : -1
		},
		{
			"ID" : -1
		},
		{
			"ID" : -1
		},
		{
			"ID" : -1
		},
		{
			"ID" : -1
		},
		{
			"ID" : -1
		},
		{
			"ID" : -1
		},
		{
			"ID" : -1
		},
		{
			"ID" : -1
		},
		{
			"ID" : -1
		},
		{
			"ID" : -1
		},
		{
			"ID" : -1
		},
		{
			"ID" : -1
		},
		{
			"ID" : -1
		},
		{
			"ID" : -1
		},
		{
			"ID" : -1
		},
		{
			"ID" : -1
		},
		{
			"ID" : -1
		},
		{
			"ID" : -1
		},
		{
			"ID" : -1
		},
		{
			"ID" : -1
		},
		{
			"ID" : -1
		},
		{
			"ID" : -1
		},
		{
			"ID" : -1
		}
	],
	"equippedItemSlot" : 0,
	"food" : 20,
	"foodExhaustion" : 0.36615000000000003,
	"foodSaturation" : 5.0,
	"foodTickTimer" : 18,
	"gamemode" : 0,
	"health" : 20.0,
	"inventory" : 
	[
		{
			"ID" : -1
		},
		{
			"ID" : -1
		},
		{
			"ID" : -1
		},
		{
			"ID" : -1
		},
		{
			"ID" : -1
		},
		{
			"ID" : -1
		},
		{
			"ID" : -1
		},
		{
			"ID" : -1
		},
		{
			"ID" : -1
		},
		{
			"ID" : -1
		},
		{
			"ID" : -1
		},
		{
			"ID" : -1
		},
		{
			"ID" : -1
		},
		{
			"ID" : -1
		},
		{
			"ID" : -1
		},
		{
			"ID" : -1
		},
		{
			"ID" : -1
		},
		{
			"ID" : -1
		},
		{
			"ID" : -1
		},
		{
			"ID" : -1
		},
		{
			"ID" : -1
		},
		{
			"ID" : -1
		},
		{
			"ID" : -1
		},
		{
			"ID" : -1
		},
		{
			"ID" : -1
		},
		{
			"ID" : -1
		},
		{
			"ID" : -1
		},
		{
			"ID" : -1
		},
		{
			"ID" : -1
		},
		{
			"ID" : -1
		},
		{
			"ID" : -1
		},
		{
			"ID" : -1
		},
		{
			"ID" : -1
		},
		{
			"ID" : -1
		},
		{
			"ID" : -1
		},
		{
			"ID" : -1
		},
		{
			"ID" : -1
		},
		{
			"ID" : -1
		},
		{
			"ID" : -1
		},
		{
			"ID" : -1
		},
		{
			"ID" : -1
		},
		{
			"ID" : -1
		},
		{
			"ID" : -1
		},
		{
			"ID" : -1
		},
		{
			"ID" : -1
		},
		{
			"ID" : -1
		}
	],
	"isflying" : false,
	"knownItems" : 
	[
		{
			"Count" : 1,
			"Health" : 0,
			"ID" : 3,
			"RepairCost" : 0
		},
		{
			"Count" : 1,
			"Health" : 0,
			"ID" : 276,
			"RepairCost" : 0
		}
	],
	"knownRecipes" : null,
	"lastknownname" : "YTSodaCan2",
	"position" : 
	[
		-6.1862125858276356,
		63.0,
		-1.7264469475074797
	],
	"rotation" : 
	[
		-40.199928283691406,
		-22.050008773803711,
		0.0
	],
	"world" : "world",
	"xpCurrent" : 0,
	"xpTotal" : 0
}